auto_corr_feature_selection/__init__.py
auto_corr_feature_selection/auto_corr_feature_selection.py
auto_corr_feature_selection-0.1.3.dist-info/METADATA
auto_corr_feature_selection-0.1.3.dist-info/WHEEL
auto_corr_feature_selection-0.1.3.dist-info/RECORD
