Metadata-Version: 2.1
Name: auto-corr-feature-selection
Version: 0.1.3
Summary: Automatically select the most relevant features based on correlation.
Home-page: https://github.com/andresdigiovanni/auto-corr-feature-selection
License: MIT
Author: Andrés Di Giovanni
Author-email: andresdigiovanni@gmail.com
Requires-Python: >=3.9
Classifier: License :: OSI Approved :: MIT License
Classifier: Programming Language :: Python :: 3
Classifier: Programming Language :: Python :: 3.9
Classifier: Programming Language :: Python :: 3.10
Classifier: Programming Language :: Python :: 3.11
Requires-Dist: numpy (>=1.25.1,<2.0.0)
Requires-Dist: pandas (>1.5.0)
Requires-Dist: scikit-learn (>=1.3.0,<2.0.0)
